subadmin/__init__.py
subadmin/templates/subadmin/breadcrumbs.html
subadmin/templates/subadmin/change_form.html
subadmin/templates/subadmin/change_list.html
subadmin/templates/subadmin/delete_confirmation.html
subadmin/templates/subadmin/delete_selected_confirmation.html
subadmin/templates/subadmin/object_history.html
subadmin/templates/subadmin/parent_change_form.html
subadmin/templates/subadmin/submit_line.html
subadmin/templatetags/__init__.py
subadmin/templatetags/subadmin_tags.py
django_subadmin-3.2.4.dist-info/LICENSE
django_subadmin-3.2.4.dist-info/METADATA
django_subadmin-3.2.4.dist-info/WHEEL
django_subadmin-3.2.4.dist-info/top_level.txt
django_subadmin-3.2.4.dist-info/RECORD
