Metadata-Version: 2.1
Name: django-subadmin
Version: 3.2.4
Summary: A special kind of ModelAdmin that allows it to be nested within another ModelAdmin
Author-email: Mitja Pagon <mitja@inueni.com>
License: MIT
Project-URL: Homepage, https://github.com/inueni/django-subadmin/
Project-URL: Bug Tracker, https://github.com/inueni/django-subadmin/issues
Project-URL: Changelog, https://github.com/inueni/django-subadmin/releases
Keywords: django,admin,modeladmin,foreignkey,related field
Classifier: Development Status :: 5 - Production/Stable
Classifier: Environment :: Web Environment
Classifier: Intended Audience :: Developers
Classifier: Operating System :: OS Independent
Classifier: License :: OSI Approved :: MIT License
Classifier: Topic :: Software Development :: Libraries :: Python Modules
Classifier: Programming Language :: Python
Classifier: Programming Language :: Python :: 3
Classifier: Framework :: Django
Classifier: Framework :: Django :: 3.2
Classifier: Framework :: Django :: 4
Requires-Python: >=3.6
License-File: LICENSE
